{
  "schemaVersion": "doctrine.advanced-connector.manifest.v1",
  "id": "dependency-track",
  "title": "Dependency-Track",
  "category": "sbom-vulnerability-management",
  "supportedModes": [
    "fixture"
  ],
  "optionalLiveMode": null,
  "fixturePath": "labs/supply-chain/connectors/dependency-track/fixtures/project-metrics.json",
  "drepsOutputPath": "labs/supply-chain/connectors/out/dependency-track/evidence-pack.json",
  "mapping": {
    "entities": "nodes",
    "relationships": "edges",
    "findings": "findings",
    "remediations": "remediations",
    "complianceImpacts": "complianceImpacts"
  }
}
